[
    {
        "id": "1",
        "video": "./video-plataforma/video1.mp4"
    },
    {
        "id": "2",
        "video": "./video-plataforma/video2.mp4"
    },
    {
        "id": "3",
        "video": "./video-plataforma/video3.mp4"
    },
    {
        "id": "4",
        "video": "./video-plataforma/video4.mp4"
    },
    {
        "id": "5",
        "video": "./video-plataforma/video5.mp4"
    },
    {
        "id": "6",
        "video": "./video-plataforma/video6.mp4"
    },
    {
        "id": "7",
        "video": "./video-plataforma/video7.mp4"
    },
    {
        "id": "8",
        "video": "./video-plataforma/video8.mp4"
    },
    {
        "id": "9",
        "video": "./video-plataforma/video9.mp4"
    },
    {
        "id": "10",
        "video": "./video-plataforma/video10.mp4"
    },
    {
        "id": "11",
        "video": "./video-plataforma/video11.mp4"
    },
    
    
    {
        "id": "13",
        "video": "./video-plataforma/video13.mp4"
    }

]